MANIFEST.in
README.rst
setup.py
turberfield/ipc/__init__.py
turberfield/ipc/cli.py
turberfield/ipc/delivery.py
turberfield/ipc/flow.py
turberfield/ipc/fsdb.py
turberfield/ipc/message.py
turberfield/ipc/netstrings.py
turberfield/ipc/node.py
turberfield/ipc/policy.py
turberfield/ipc/proactor.py
turberfield/ipc/types.py
turberfield/ipc/udp.py
turberfield/ipc/demo/__init__.py
turberfield/ipc/demo/initiator.py
turberfield/ipc/demo/processor.py
turberfield/ipc/demo/router.py
turberfield/ipc/demo/sender.py
turberfield/ipc/doc/index.rst
turberfield/ipc/doc/message.rst
turberfield/ipc/doc/netstrings.rst
turberfield/ipc/doc/node.rst
turberfield/ipc/doc/node_example.rst
turberfield/ipc/doc/proactor.rst
turberfield/ipc/doc/proactor_example.rst
turberfield/ipc/doc/protocol.rst
turberfield/ipc/doc/html/genindex.html
turberfield/ipc/doc/html/index.html
turberfield/ipc/doc/html/message.html
turberfield/ipc/doc/html/netstrings.html
turberfield/ipc/doc/html/node.html
turberfield/ipc/doc/html/node_example.html
turberfield/ipc/doc/html/proactor.html
turberfield/ipc/doc/html/proactor_example.html
turberfield/ipc/doc/html/protocol.html
turberfield/ipc/doc/html/py-modindex.html
turberfield/ipc/doc/html/search.html
turberfield/ipc/doc/html/searchindex.js
turberfield/ipc/doc/html/_sources/index.rst.txt
turberfield/ipc/doc/html/_sources/message.rst.txt
turberfield/ipc/doc/html/_sources/netstrings.rst.txt
turberfield/ipc/doc/html/_sources/node.rst.txt
turberfield/ipc/doc/html/_sources/node_example.rst.txt
turberfield/ipc/doc/html/_sources/proactor.rst.txt
turberfield/ipc/doc/html/_sources/proactor_example.rst.txt
turberfield/ipc/doc/html/_sources/protocol.rst.txt
turberfield/ipc/doc/html/_static/ajax-loader.gif
turberfield/ipc/doc/html/_static/alert_info_32.png
turberfield/ipc/doc/html/_static/alert_warning_32.png
turberfield/ipc/doc/html/_static/basic.css
turberfield/ipc/doc/html/_static/bg-page.png
turberfield/ipc/doc/html/_static/bullet_orange.png
turberfield_ipc.egg-info/PKG-INFO
turberfield_ipc.egg-info/SOURCES.txt
turberfield_ipc.egg-info/dependency_links.txt
turberfield_ipc.egg-info/entry_points.txt
turberfield_ipc.egg-info/namespace_packages.txt
turberfield_ipc.egg-info/not-zip-safe
turberfield_ipc.egg-info/requires.txt
turberfield_ipc.egg-info/top_level.txt