Metadata-Version: 1.1
Name: turberfield-ipc
Version: 0.15.0
Summary: A Distributed Inter-Process Control Facility from the Turberfield project.
Home-page: https://www.assembla.com/spaces/turberfield/messages
Author: D Haynes
Author-email: tundish@thuswise.org
License: UNKNOWN
Platform: UNKNOWN
Classifier: Operating System :: POSIX
Classifier: Programming Language :: Python :: 3.5
Classifier: License :: OSI Approved :: GNU General Public License v3 or later (GPLv3+)
